timestrader_preprocessing/__init__.py
timestrader_preprocessing/common/__init__.py
timestrader_preprocessing/common/models.py
timestrader_preprocessing/common/utils.py
timestrader_preprocessing/config/__init__.py
timestrader_preprocessing/config/defaults.py
timestrader_preprocessing/config/normalization_story_1_7 2.json
timestrader_preprocessing/config/normalization_story_1_7.json
timestrader_preprocessing/historical/__init__.py
timestrader_preprocessing/historical/indicators.py
timestrader_preprocessing/historical/processor.py
timestrader_preprocessing/historical/validation.py
timestrader_preprocessing/realtime/__init__.py
timestrader_preprocessing/realtime/streaming.py
timestrader_preprocessing-1.1.2.dist-info/METADATA
timestrader_preprocessing-1.1.2.dist-info/WHEEL
timestrader_preprocessing-1.1.2.dist-info/licenses/LICENSE
timestrader_preprocessing-1.1.2.dist-info/RECORD
