Metadata-Version: 2.4
Name: timestrader-preprocessing
Version: 1.1.2
Summary: Canonical preprocessing toolkit for TimesTrader Story 1.7
Project-URL: Homepage, https://github.com/timestrader/timestrader-v05
Project-URL: Repository, https://github.com/timestrader/timestrader-v05
Project-URL: Documentation, https://timestrader.readthedocs.io
Project-URL: Issues, https://github.com/timestrader/timestrader-v05/issues
Project-URL: Changelog, https://github.com/timestrader/timestrader-v05/blob/main/timestrader-preprocessing/CHANGELOG.md
Author-email: TimeStrader Team <team@timestrader.ai>
License: MIT
License-File: LICENSE
Keywords: normalization,preprocessing,quantitative,timesnet,trading
Classifier: Development Status :: 4 - Beta
Classifier: Intended Audience :: Developers
Classifier: Intended Audience :: Financial and Insurance Industry
Classifier: License :: OSI Approved :: MIT License
Classifier: Operating System :: OS Independent
Classifier: Programming Language :: Python :: 3
Classifier: Programming Language :: Python :: 3.10
Classifier: Programming Language :: Python :: 3.11
Classifier: Programming Language :: Python :: 3.12
Classifier: Topic :: Scientific/Engineering :: Artificial Intelligence
Requires-Python: >=3.10
Requires-Dist: numpy>=1.26.0
Requires-Dist: pandas>=2.1.0
Requires-Dist: scikit-learn>=1.3.0
Requires-Dist: tqdm>=4.66.0
Provides-Extra: dev
Requires-Dist: black>=23.0.0; extra == 'dev'
Requires-Dist: build>=1.0.0; extra == 'dev'
Requires-Dist: mypy>=1.6.0; extra == 'dev'
Requires-Dist: psutil>=5.9.0; extra == 'dev'
Requires-Dist: pytest-cov>=4.0.0; extra == 'dev'
Requires-Dist: pytest>=7.4.0; extra == 'dev'
Requires-Dist: ruff>=0.6.0; extra == 'dev'
Requires-Dist: twine>=4.0.0; extra == 'dev'
